<?xml version="1.0" encoding="UTF-8"?><record_update sys_domain="global" table="m2m_app_config_theme">
    <m2m_app_config_theme action="INSERT_OR_UPDATE">
        <applicability display_value="Public">5d517bace4b13110c2418ac5fcb6660e</applicability>
        <order>0</order>
        <sys_class_name>m2m_app_config_theme</sys_class_name>
        <sys_created_by>system</sys_created_by>
        <sys_created_on>2023-10-07 14:57:46</sys_created_on>
        <sys_domain>global</sys_domain>
        <sys_domain_path>/</sys_domain_path>
        <sys_id>11517bac6ab13110e86df977e74fb10f</sys_id>
        <sys_mod_count>0</sys_mod_count>
        <sys_name/>
        <sys_overrides/>
        <sys_package display_value="Demo" source="x_53417_demo">785f7e9b97161110fa6733121153afdb</sys_package>
        <sys_policy/>
        <sys_scope display_value="Demo">785f7e9b97161110fa6733121153afdb</sys_scope>
        <sys_update_name>m2m_app_config_theme_11517bac6ab13110e86df977e74fb10f</sys_update_name>
        <sys_updated_by>system</sys_updated_by>
        <sys_updated_on>2023-10-07 14:57:46</sys_updated_on>
        <theme display_value="Light Theme">95517bac81b13110760de4b26a45860f</theme>
        <ux_app_configuration display_value="Demo AES Portal Config">b4513bac97b1311024d7b066f053af86</ux_app_configuration>
    </m2m_app_config_theme>
</record_update>
